meter_detection-0.3.2.dist-info/METADATA
meter_detection-0.3.2.dist-info/WHEEL
meter_detection-0.3.2.dist-info/entry_points.txt
meter_detection/__init__.py
meter_detection/apicall/__init__.py
meter_detection/data_process.py
meter_detection/dataset.py
meter_detection/k/algo/keypoint/dataset.py
meter_detection/k/algo/keypoint/model.py
meter_detection/k/algo/keypoint/train.py
meter_detection/k/algo/keypoint/utils.py
meter_detection/k/algo/meterkeypoint/dataset.py
meter_detection/k/algo/meterkeypoint/model.py
meter_detection/k/model.py
meter_detection/k/schema.py
meter_detection/model.py
meter_detection/schema.py
meter_detection/train.py
meter_detection/visual.py
meter_detection-0.3.2.dist-info/RECORD
