Metadata-Version: 2.1
Name: meter_detection
Version: 0.3.2
Summary: a library for meter detection
Author-Email: svtter <svtter@qq.com>
License: MIT
Requires-Python: <4.0,>=3.9
Requires-Dist: numpy<2.0
Requires-Dist: pydantic>2.0
Requires-Dist: imgaug>=0.4.0
